VuejsDoc/README.md
VuejsDoc/__init__.py
VuejsDoc/__main__.py
VuejsDoc/file.epub
VuejsDoc/index.html
VuejsDoc/css/__init__.py
VuejsDoc/css/annotations.css
VuejsDoc/css/main.css
VuejsDoc/css/normalize.css
VuejsDoc/css/popup.css
VuejsDoc/font/__init__.py
VuejsDoc/font/fontello.eot
VuejsDoc/font/fontello.svg
VuejsDoc/font/fontello.ttf
VuejsDoc/font/fontello.woff
VuejsDoc/img/__init__.py
VuejsDoc/img/annotator-glyph-sprite.png
VuejsDoc/img/annotator-icon-sprite.png
VuejsDoc/img/apple-touch-icon.png
VuejsDoc/img/cancelfullscreen.png
VuejsDoc/img/close.png
VuejsDoc/img/fullscreen.png
VuejsDoc/img/loader.gif
VuejsDoc/img/menu-icon.png
VuejsDoc/img/save.png
VuejsDoc/img/saved.png
VuejsDoc/img/settings-s.png
VuejsDoc/img/settings.png
VuejsDoc/img/star.png
VuejsDoc/js/__init__.py
VuejsDoc/js/epub.js
VuejsDoc/js/epub.min.js
VuejsDoc/js/epub.min.map
VuejsDoc/js/hooks.min.js
VuejsDoc/js/hooks.min.map
VuejsDoc/js/reader.js
VuejsDoc/js/reader.js.map
VuejsDoc/js/reader.min.js
VuejsDoc/js/reader.min.map
VuejsDoc/js/hooks/__init__.py
VuejsDoc/js/hooks/extensions/__init__.py
VuejsDoc/js/hooks/extensions/highlight.js
VuejsDoc/js/libs/__init__.py
VuejsDoc/js/libs/jquery.min.js
VuejsDoc/js/libs/localforage.min.js
VuejsDoc/js/libs/screenfull.js
VuejsDoc/js/libs/screenfull.min.js
VuejsDoc/js/libs/zip.min.js
VuejsDoc/js/plugins/__init__.py
VuejsDoc/js/plugins/hypothesis.js
VuejsDoc/js/plugins/search.js
vuejs_doc-2024.3.2.0.dist-info/METADATA
vuejs_doc-2024.3.2.0.dist-info/WHEEL
vuejs_doc-2024.3.2.0.dist-info/entry_points.txt
vuejs_doc-2024.3.2.0.dist-info/top_level.txt
vuejs_doc-2024.3.2.0.dist-info/RECORD
